{
	"pages": [ //pages数组中第一项表示应用启动页,
		{
			"path": "pages/main/main",
			"style": {
				"app-plus": {
					"titleNView": false
				}
			}
		}, {
			"path": "pages/login/login",
			"style": {
				"app-plus": {
					"titleNView": false
				}
			}
		}, {
			"path": "pages/reg/reg",
			"style": {
				"app-plus": {
					"titleNView": false
				}
			}
		}, {
			"path": "pages/pwd/pwd",
			"style": {
				"navigationBarTitleText": "找回密码"
			}
		}, {
			"path": "pages/user/user",
			"style": {
				"app-plus": {
					"titleNView": false
				}
			}
		}, {
			"path": "pages/store/store",
			"style": {
				"app-plus": {
					"titleNView": false
				}
			}
		}, {
			"path": "pages/task/task",
			"style": {
				"app-plus": {
					"titleNView": false
				}
			}
		}
        ,{
            "path" : "pages/detail/detail",
            "style" : {
				"navigationBarBackgroundColor": "#16161B"
			}
        },
		{
		   "path" : "pages/task/attestation",
			"style" : {
				"navigationBarTitleText": "实名认证",
				"navigationBarBackgroundColor": "#1F1F26"
			}
		}
        ,{
            "path" : "pages/team/team",
            "style" : {
            	"navigationBarTitleText": "我的团队",
            	"navigationBarBackgroundColor": "#1F1F26"
            }
        }
    ],
	"tabBar": {
		"color": "#686c6f",
		"selectedColor": "#dfb67d",
		"backgroundColor": "#1f1f26",
		"list": [{
			"pagePath": "pages/main/main",
			"text": "短视频",
			"iconPath": "static/img/shipin.png",
			"selectedIconPath": "static/img/shipincheck.png"
		}, {
			"pagePath": "pages/task/task",
			"text": "任务",
			"iconPath": "static/img/renwu.png",
			"selectedIconPath": "static/img/renwucheck.png"
		}, {
			"pagePath": "pages/store/store",
			"text": "商城",
			"iconPath": "static/img/shangcheng.png",
			"selectedIconPath": "static/img/shangchengcheck.png"
		}, {
			"pagePath": "pages/user/user",
			"text": "我的",
			"iconPath": "static/img/wode.png",
			"selectedIconPath": "static/img/userHL.png"
		}]
	},
	"globalStyle": {
		"navigationBarTextStyle": "white",
		"navigationBarBackgroundColor": "#0faeff",
		"backgroundColor": "#fbf9fe"
	}
}
